freelunch/__init__.py
freelunch/adaptable.py
freelunch/base.py
freelunch/benchmarks.py
freelunch/darwin.py
freelunch/optimisers.py
freelunch/tech.py
freelunch/util.py
freelunch/zoo.py
freelunch-0.0.15.dist-info/LICENSE
freelunch-0.0.15.dist-info/METADATA
freelunch-0.0.15.dist-info/WHEEL
freelunch-0.0.15.dist-info/top_level.txt
freelunch-0.0.15.dist-info/RECORD
