Metadata-Version: 2.1
Name: freelunch
Version: 0.0.15
Summary: Heuristic and meta-heuristic optimisation suite in Python
Home-page: https://github.com/MDCHAMP/FreeLunch
Author: Max Champneys
Author-email: max.champneys@gmail.com
License: MIT
Platform: UNKNOWN
Classifier: License :: OSI Approved :: MIT License
Classifier: Programming Language :: Python :: 3
Classifier: Intended Audience :: Science/Research
License-File: LICENSE
Requires-Dist: numpy
